polymarket/__init__.py
polymarket/__main__.py
polymarket/buy.py
polymarket/cli.py
polymarket/liquidity.py
polymarket/markets.py
polymarket/merge.py
polymarket/positions.py
polymarket/redeem.py
polymarket/sell.py
polymarket/split.py
polymarket/utils.py
polymarket/abi/ConditionalTokens.json
polymarket/abi/ERC1155.json
polymarket/abi/ERC20.json
polymarket/abi/FixedProductMarketMaker.json
polymarket/abi/__init__.py
polymarket/amm/__init__.py
polymarket/amm/maths.py
polymarket/gql/__init__.py
polymarket/gql/positions.gql
polymarket_trading-0.1.8.dist-info/LICENSE
polymarket_trading-0.1.8.dist-info/METADATA
polymarket_trading-0.1.8.dist-info/WHEEL
polymarket_trading-0.1.8.dist-info/entry_points.txt
polymarket_trading-0.1.8.dist-info/top_level.txt
polymarket_trading-0.1.8.dist-info/RECORD
