Metadata-Version: 2.1
Name: polymarket-trading
Version: 0.1.8
Summary: A collection of tools for trading on polymarket.com
Home-page: https://github.com/PolyTrader/polymarket-trading
Author: PolyTrader
License: UNKNOWN
Platform: UNKNOWN
Classifier: Programming Language :: Python :: 3
Classifier: License :: OSI Approved :: MIT License
Classifier: Operating System :: OS Independent
Requires-Python: >=3.6
License-File: LICENSE
Requires-Dist: web3
Requires-Dist: importlib-resources
Requires-Dist: eth-account
Requires-Dist: requests
Requires-Dist: gql
Requires-Dist: mpmath
Requires-Dist: pydash
Requires-Dist: requests-toolbelt
